summary_stack_mcp_core/__init__.py
summary_stack_mcp_core/api_client.py
summary_stack_mcp_core/config.py
summary_stack_mcp_core/tools.py
summary_stack_mcp_core-0.1.0.dist-info/METADATA
summary_stack_mcp_core-0.1.0.dist-info/WHEEL
summary_stack_mcp_core-0.1.0.dist-info/RECORD
